cv2/LICENSE-3RD-PARTY.txt
cv2/LICENSE.txt
cv2/__init__.py
cv2/__init__.pyi
cv2/config-3.py
cv2/config.py
cv2/cv2.pyd
cv2/load_config_py2.py
cv2/load_config_py3.py
cv2/opencv_videoio_ffmpeg4130.dll
cv2/py.typed
cv2/version.py
cv2/Error/__init__.pyi
cv2/aruco/__init__.pyi
cv2/barcode/__init__.pyi
cv2/bgsegm/__init__.pyi
cv2/bioinspired/__init__.pyi
cv2/ccm/__init__.pyi
cv2/colored_kinfu/__init__.pyi
cv2/cuda/__init__.pyi
cv2/data/__init__.py
cv2/data/haarcascade_eye.xml
cv2/data/haarcascade_eye_tree_eyeglasses.xml
cv2/data/haarcascade_frontalcatface.xml
cv2/data/haarcascade_frontalcatface_extended.xml
cv2/data/haarcascade_frontalface_alt.xml
cv2/data/haarcascade_frontalface_alt2.xml
cv2/data/haarcascade_frontalface_alt_tree.xml
cv2/data/haarcascade_frontalface_default.xml
cv2/data/haarcascade_fullbody.xml
cv2/data/haarcascade_lefteye_2splits.xml
cv2/data/haarcascade_license_plate_rus_16stages.xml
cv2/data/haarcascade_lowerbody.xml
cv2/data/haarcascade_profileface.xml
cv2/data/haarcascade_righteye_2splits.xml
cv2/data/haarcascade_russian_plate_number.xml
cv2/data/haarcascade_smile.xml
cv2/data/haarcascade_upperbody.xml
cv2/datasets/__init__.pyi
cv2/detail/__init__.pyi
cv2/dnn/__init__.pyi
cv2/dnn_superres/__init__.pyi
cv2/dpm/__init__.pyi
cv2/dynafu/__init__.pyi
cv2/face/__init__.pyi
cv2/fisheye/__init__.pyi
cv2/flann/__init__.pyi
cv2/ft/__init__.pyi
cv2/gapi/__init__.py
cv2/gapi/__init__.pyi
cv2/gapi/core/__init__.pyi
cv2/gapi/core/cpu/__init__.pyi
cv2/gapi/core/fluid/__init__.pyi
cv2/gapi/core/ocl/__init__.pyi
cv2/gapi/ie/__init__.pyi
cv2/gapi/ie/detail/__init__.pyi
cv2/gapi/imgproc/__init__.pyi
cv2/gapi/imgproc/fluid/__init__.pyi
cv2/gapi/oak/__init__.pyi
cv2/gapi/onnx/__init__.pyi
cv2/gapi/onnx/ep/__init__.pyi
cv2/gapi/ot/__init__.pyi
cv2/gapi/ot/cpu/__init__.pyi
cv2/gapi/ov/__init__.pyi
cv2/gapi/own/__init__.pyi
cv2/gapi/own/detail/__init__.pyi
cv2/gapi/render/__init__.pyi
cv2/gapi/render/ocv/__init__.pyi
cv2/gapi/streaming/__init__.pyi
opencv_contrib_python_headless-4.13.0.90.dist-info/LICENSE-3RD-PARTY.txt
opencv_contrib_python_headless-4.13.0.90.dist-info/LICENSE.txt
opencv_contrib_python_headless-4.13.0.90.dist-info/METADATA
opencv_contrib_python_headless-4.13.0.90.dist-info/WHEEL
opencv_contrib_python_headless-4.13.0.90.dist-info/top_level.txt
opencv_contrib_python_headless-4.13.0.90.dist-info/RECORD
